jaweson
