Metadata-Version: 1.1
Name: jaweson
Version: 1.3.1
Summary: A safe, modular, format agnostic, serialiser. Provides support for JSON, MsgPack
Home-page: https://github.com/someones/jaweson
Author: Adam Griffiths
Author-email: UNKNOWN
License: BSD
Platform: any
Classifier: Natural Language :: English
Classifier: Intended Audience :: Developers
Classifier: Operating System :: MacOS :: MacOS X
Classifier: Operating System :: Microsoft :: Windows
Classifier: Operating System :: POSIX
Classifier: Programming Language :: Python
Classifier: License :: OSI Approved :: BSD License
Classifier: Topic :: Software Development :: Libraries
Classifier: Topic :: Software Development :: Libraries :: Python Modules
